[["dziennik", "brev:pun"], [".", "interp"], ["ustawa", "brev:pun"], [".", "interp"], ["z", "prep:gen:nwok"], ["2001", "adj:sg:gen:m3:pos"], ["rok", "brev:pun"], [".", "interp"], ["numer", "brev:npun"], ["102", "num:pl:nom:m3:congr"], [",", "interp"], ["pozycja", "brev:pun"], [".", "interp"], ["1118", "adj:sg:nom:f:pos"], ["ustawa", "subst:sg:nom:f"], ["z", "prep:gen:nwok"], ["dzień", "subst:sg:gen:m3"], ["23", "adj:sg:gen:m3:pos"], ["sierpień", "subst:sg:gen:m3"], ["2001", "adj:sg:gen:m3:pos"], ["rok", "brev:pun"], [".", "interp"], ["o", "prep:loc"], ["zmiana", "subst:sg:loc:f"], ["ustawa", "subst:sg:gen:f"], ["o", "prep:loc"], ["zasada", "subst:pl:loc:f"], ["zbywać", "ger:sg:gen:n:imperf:aff"], ["mieszkanie", "subst:pl:gen:n"], ["być", "pact:pl:gen:n:imperf:aff"], ["własność", "subst:sg:inst:f"], ["przedsiębiorstwo", "subst:pl:gen:n"], ["państwowy", "adj:pl:gen:n:pos"], [",", "interp"], ["niektóry", "adj:pl:gen:f:pos"], ["spółka", "subst:pl:gen:f"], ["handlowy", "adj:pl:gen:f:pos"], ["z", "prep:inst:nwok"], ["udział", "subst:sg:inst:m3"], ["skarb", "subst:sg:gen:m3"], ["państwo", "subst:sg:gen:n"], [",", "interp"], ["państwowy", "adj:pl:gen:f:pos"], ["osoba", "subst:pl:gen:f"], ["prawny", "adj:pl:gen:f:pos"], ["oraz", "conj"], ["niektóry", "adj:pl:gen:n:pos"], ["mieszkanie", "subst:pl:gen:n"], ["być", "pact:pl:gen:n:imperf:aff"], ["własność", "subst:sg:inst:f"], ["skarb", "subst:sg:gen:m3"], ["państwo", "subst:sg:gen:n"], ["Art", "subst:sg:nom:m3"], [".", "interp"], ["1", "adj:sg:gen:m3:pos"], [".", "interp"], ["w", "prep:loc:nwok"], ["ustawa", "subst:sg:loc:f"], ["z", "prep:gen:nwok"], ["dzień", "subst:sg:gen:m3"], ["15", "adj:sg:gen:m3:pos"], ["grudzień", "subst:sg:gen:m3"], ["2000", "adj:sg:gen:m3:pos"], ["rok", "brev:pun"], [".", "interp"], ["o", "prep:loc"], ["zasada", "subst:pl:loc:f"], ["zbywać", "ger:sg:gen:n:imperf:aff"], ["mieszkanie", "subst:pl:gen:n"], ["być", "pact:pl:gen:n:imperf:aff"], ["własność", "subst:sg:inst:f"], ["przedsiębiorstwo", "subst:pl:gen:n"], ["państwowy", "adj:pl:gen:n:pos"], [",", "interp"], ["niektóry", "adj:pl:gen:f:pos"], ["spółka", "subst:pl:gen:f"], ["handlowy", "adj:pl:gen:f:pos"], ["z", "prep:inst:nwok"], ["udział", "subst:sg:inst:m3"], ["skarb", "subst:sg:gen:m3"], ["państwo", "subst:sg:gen:n"], [",", "interp"], ["państwowy", "adj:pl:gen:f:pos"], ["osoba", "subst:pl:gen:f"], ["prawny", "adj:pl:gen:f:pos"], ["oraz", "conj"], ["niektóry", "adj:pl:gen:n:pos"], ["mieszkanie", "subst:pl:gen:n"], ["być", "pact:pl:gen:n:imperf:aff"], ["własność", "subst:sg:inst:f"], ["skarb", "subst:sg:gen:m3"], ["państwo", "subst:sg:gen:n"], ["(", "interp"], ["dziennik", "brev:pun"], [".", "interp"], ["ustawa", "brev:pun"], [".", "interp"], ["z", "prep:gen:nwok"], ["2001", "adj:sg:gen:m3:pos"], ["rok", "brev:pun"], [".", "interp"], ["numer", "brev:npun"], ["4", "num:pl:nom:m3:congr"], [",", "interp"], ["pozycja", "brev:pun"], [".", "interp"], ["24", "adj:sg:nom:f:pos"], [")", "interp"], ["wprowadzać", "fin:sg:ter:imperf"], ["się", "qub"], ["następujący", "adj:pl:acc:f:pos"], ["zmiana", "subst:pl:acc:f"], [":", "interp"], ["1", "adj:sg:nom:n:pos"], [")", "interp"], ["w", "prep:loc:nwok"], ["artykuł", "brev:pun"], [".", "interp"], ["1", "adj:sg:loc:m3:pos"], ["dodawać", "fin:sg:ter:imperf"], ["się", "qub"], ["ustęp", "brev:pun"], [".", "interp"], ["2a", "subst:sg:nom:n"], ["w", "prep:loc:nwok"], ["brzmienie", "subst:sg:loc:n"], [":", "interp"], ["\"", "interp"], ["2a", "subst:sg:nom:n"], [".", "interp"], ["ustawa", "subst:sg:nom:f"], ["dotyczyć", "fin:sg:ter:imperf"], ["także", "qub"], ["zbywca", "subst:pl:gen:m1"], [",", "interp"], ["o", "prep:loc"], ["który", "adj:pl:loc:m1:pos"], ["mowa", "subst:sg:nom:f"], ["w", "prep:loc:nwok"], ["artykuł", "brev:pun"], [".", "interp"], ["2", "adj:sg:loc:m3:pos"], ["punkt", "brev:npun"], ["1", "adj:sg:nom:m3:pos"], [",", "interp"], ["być", "pact:pl:gen:m1:imperf:aff"], ["w", "prep:loc:nwok"], ["likwidacja", "subst:sg:loc:f"], ["lub", "conj"], ["upadłość", "subst:sg:loc:f"], [".", "interp"], ["\"", "interp"], [";", "interp"], ["2", "adj:sg:nom:n:pos"], [")", "interp"], ["w", "prep:loc:nwok"], ["artykuł", "brev:pun"], [".", "interp"], ["2", "adj:sg:loc:m3:pos"], [":", "interp"], ["a", "subst:sg:nom:n"], [")", "interp"], ["w", "prep:loc:nwok"], ["punkt", "brev:npun"], ["1", "adj:sg:loc:m3:pos"], [":", "interp"], ["-", "interp"], ["w", "prep:acc:nwok"], ["litera", "brev:pun"], [".", "interp"], ["a", "subst:sg:nom:n"], [")", "interp"], ["skreślać", "fin:sg:ter:imperf"], ["się", "qub"], ["wyraz", "subst:pl:acc:m3"], ["\"", "interp"], ["z", "prep:inst:nwok"], ["wyłączenie", "subst:sg:inst:n"], ["przedsiębiorstwo", "subst:sg:gen:n"], ["państwowy", "adj:sg:gen:n:pos"], ["polski", "adj:pl:nom:f:pos"], ["kolej", "subst:pl:nom:f"], ["państwowy", "adj:pl:acc:f:pos"], [",", "interp"], ["\"", "interp"], [",", "interp"], ["-", "interp"], ["w", "prep:acc:nwok"], ["lit", "subst:sg:acc:m3"], ["b", "subst:sg:nom:n"], [")", "interp"], ["na", "prep:loc"], ["koniec", "subst:sg:loc:m3"], ["dodawać", "fin:sg:ter:imperf"], ["się", "qub"], ["wyraz", "subst:pl:acc:m3"], ["\"", "interp"], ["z", "prep:inst:nwok"], ["wyłączyć", "ger:sg:inst:n:perf:aff"], ["polski", "adj:pl:gen:f:pos"], ["kolej", "subst:pl:gen:f"], ["państwowy", "adj:pl:gen:f:pos"], ["spółka", "subst:sg:gen:f"], ["akcyjny", "adj:sg:gen:f:pos"], [",", "interp"], ["\"", "interp"], [",", "interp"], ["b", "subst:sg:nom:n"], [")", "interp"], ["dodawać", "fin:sg:ter:imperf"], ["się", "qub"], ["punkt", "brev:npun"], ["1a", "subst:sg:nom:n"], ["w", "prep:loc:nwok"], ["brzmienie", "subst:sg:loc:n"], [":", "interp"], ["\"", "interp"], ["1a", "subst:sg:nom:n"], [")", "interp"], ["poprzednik", "subst:sg:loc:m3"], ["prawny", "adj:sg:loc:m3:pos"], ["zbywca", "subst:sg:gen:m1"], ["-", "interp"], ["należeć", "fin:sg:ter:imperf"], ["przez", "prep:acc:nwok"], ["to", "subst:sg:acc:n"], ["rozumieć", "inf:imperf"], ["podmiot", "subst:pl:acc:m3"], [",", "interp"], ["o", "prep:loc"], ["który", "adj:pl:loc:m3:pos"], ["mowa", "subst:sg:nom:f"], ["w", "prep:loc:nwok"], ["artykuł", "brev:pun"], [".", "interp"], ["1", "adj:sg:loc:m3:pos"], ["ustęp", "brev:pun"], [".", "interp"], ["1", "adj:sg:nom:m3:pos"], [":", "interp"], ["a", "subst:sg:nom:n"], [")", "interp"], ["jeżeli", "comp"], ["budynek", "subst:pl:nom:m3"], ["mieszkalny", "adj:pl:nom:m3:pos"], [",", "interp"], ["który", "adj:pl:nom:m3:pos"], ["stanowić", "praet:pl:m3:imperf"], ["on", "ppron3:pl:gen:m3:ter:akc:npraep"], ["własność", "subst:sg:acc:f"], ["zostać", "praet:pl:m3:perf"], ["wnieść", "ppas:pl:nom:m3:perf:aff"], ["jako", "conj"], ["wkład", "subst:sg:acc:m3"], ["niepieniężny", "adj:sg:acc:m3:pos"], ["do", "prep:gen"], ["spółka", "subst:sg:gen:f"], ["handlowy", "adj:sg:gen:f:pos"], ["albo", "conj"], ["wyposażyć", "imps:perf"], ["w", "prep:acc:nwok"], ["on", "ppron3:pl:acc:m3:ter:akc:praep"], ["przedsiębiorstwo", "subst:pl:acc:n"], ["państwowy", "adj:pl:acc:n:pos"], ["lub", "conj"], ["inny", "adj:sg:acc:f:pos"], ["państwowy", "adj:sg:acc:f:pos"], ["osoba", "subst:sg:acc:f"], ["prawny", "adj:sg:acc:f:pos"], ["być", "pact:sg:acc:f:imperf:aff"], ["zbywca", "subst:sg:inst:m1"], [",", "interp"], ["bit", "brev:npun"], [")", "interp"], ["który", "adj:pl:nom:f:pos"], ["uczestniczyć", "praet:pl:f:imperf"], ["na", "prep:loc"], ["podstawa", "subst:sg:loc:f"], ["umowa", "subst:sg:gen:f"], ["w", "prep:loc:nwok"], ["ponosić", "ger:sg:loc:n:imperf:aff"], ["koszt", "subst:pl:gen:m3"], ["budowa", "subst:sg:gen:f"], ["budynek", "subst:pl:gen:m3"], ["mieszkalny", "adj:pl:gen:m3:pos"], ["stanowić", "pact:pl:gen:m3:imperf:aff"], ["własność", "subst:sg:nom:f"], ["zbywca", "subst:sg:gen:m1"], [",", "interp"], ["\"", "interp"], [",", "interp"], ["c", "subst:sg:nom:n"], [")", "interp"], ["punkt", "brev:npun"], ["2", "adj:sg:nom:m3:pos"], ["otrzymywać", "fin:sg:ter:imperf"], ["brzmienie", "subst:sg:acc:n"], [":", "interp"], ["\"", "interp"], ["2", "adj:sg:nom:n:pos"], [")", "interp"], ["osoba", "subst:sg:dat:f"], ["uprawniony", "adj:sg:dat:f:pos"], ["-", "interp"], ["należeć", "fin:sg:ter:imperf"], ["przez", "prep:acc:nwok"], ["to", "subst:sg:acc:n"], ["rozumieć", "inf:imperf"], [":", "interp"], ["a", "subst:sg:nom:n"], [")", "interp"], ["pracownik", "subst:sg:acc:m1"], [",", "interp"], ["były", "adj:sg:acc:m1:pos"], ["pracownik", "subst:sg:acc:m1"], ["zbywca", "subst:sg:gen:m1"], ["albo", "conj"], ["on", "ppron3:sg:gen:m1:ter:akc:npraep"], ["poprzednik", "subst:sg:gen:m3"], ["prawny", "adj:sg:acc:m1:pos"], [",", "interp"], ["który", "adj:sg:nom:m1:pos"], ["być", "fin:sg:ter:imperf"], ["najemca", "subst:sg:inst:m1"], [",", "interp"], ["zajmować", "pact:sg:inst:m1:imperf:aff"], ["mieszkanie", "subst:sg:acc:n"], ["na", "prep:loc"], ["podstawa", "subst:sg:loc:f"], ["umowa", "subst:sg:gen:f"], ["najem", "subst:sg:gen:m3"], ["zawrzeć", "ppas:sg:gen:f:perf:aff"], ["na", "prep:acc"], ["czas", "subst:sg:acc:m3"], ["nieoznaczony", "adj:sg:acc:m3:pos"], ["lub", "conj"], ["administracyjny", "adj:sg:gen:f:pos"], ["decyzja", "subst:sg:gen:f"], ["o", "prep:loc"], ["przydział", "subst:sg:loc:m3"], [";", "interp"], ["za", "prep:acc"], ["osoba", "subst:sg:acc:f"], ["uprawniony", "adj:sg:acc:f:pos"], ["uznawać", "fin:sg:ter:imperf"], ["się", "qub"], ["także", "qub"], ["pracownik", "subst:sg:gen:m1"], ["zbywca", "subst:sg:gen:m1"], ["albo", "conj"], ["on", "ppron3:sg:gen:m1:ter:akc:npraep"], ["poprzednik", "subst:sg:gen:m3"], ["prawny", "adj:sg:gen:m3:pos"], [",", "interp"], ["z", "prep:inst:nwok"], ["który", "adj:sg:inst:m3:pos"], ["przed", "prep:inst:nwok"], ["dzień", "subst:sg:inst:m3"], ["12", "adj:sg:gen:m3:pos"], ["listopad", "subst:sg:gen:m3"], ["1994", "adj:sg:gen:m3:pos"], ["rok", "brev:pun"], [".", "interp"], ["zawrzeć", "imps:perf"], ["umowa", "subst:sg:acc:f"], ["najem", "subst:sg:gen:m3"], ["na", "prep:acc"], ["czas", "subst:sg:acc:m3"], ["oznaczony", "adj:sg:acc:m3:pos"], ["związany", "adj:sg:acc:f:pos"], ["z", "prep:inst:wok"], ["stosunek", "subst:sg:inst:m3"], ["praca", "subst:sg:gen:f"], [",", "interp"], ["b", "subst:sg:nom:n"], [")", "interp"], ["stale", "adv:pos"], ["zamieszkały", "adj:pl:gen:f:pos"], ["z", "prep:inst:nwok"], ["pracownik", "subst:sg:inst:m1"], ["lub", "conj"], ["były", "adj:sg:inst:m1:pos"], ["pracownik", "subst:sg:inst:m1"], ["w", "prep:loc:nwok"], ["chwila", "subst:sg:loc:f"], ["on", "ppron3:sg:gen:m1:ter:akc:npraep"], ["śmierć", "subst:sg:gen:f"], [",", "interp"], ["małżonka", "subst:sg:nom:f"], [",", "interp"], ["zstępny", "subst:sg:gen:m1"], [",", "interp"], ["wstępny", "adj:sg:gen:n:pos"], [",", "interp"], ["pełnoletni", "adj:sg:acc:n:pos"], ["rodzeństwo", "subst:sg:acc:n"], [",", "interp"], ["osoba", "subst:sg:acc:f"], ["on", "ppron3:sg:gen:m3:ter:nakc:npraep"], ["przysposabiać", "pact:sg:acc:f:imperf:aff"], ["albo", "conj"], ["przez", "prep:acc:nwok"], ["on", "ppron3:sg:acc:m1:ter:akc:praep"], ["przysposobiony", "adj:sg:acc:f:pos"], ["oraz", "conj"], ["osoba", "subst:sg:acc:f"], ["pozostawać", "pact:sg:acc:f:imperf:aff"], ["w", "prep:loc:wok"], ["wspólny", "adj:sg:loc:n:pos"], ["gospodarstwo", "subst:sg:loc:n"], ["domowy", "adj:sg:loc:n:pos"], [",", "interp"], ["\"", "interp"], [";", "interp"], ["3", "adj:sg:nom:n:pos"], [")", "interp"], ["w", "prep:loc:nwok"], ["artykuł", "brev:pun"], [".", "interp"], ["6", "adj:sg:loc:m3:pos"], [":", "interp"], ["a", "subst:sg:nom:n"], [")", "interp"], ["ustęp", "brev:pun"], [".", "interp"], ["1", "adj:sg:nom:m3:pos"], ["otrzymywać", "fin:sg:ter:imperf"], ["brzmienie", "subst:sg:acc:n"], [":", "interp"], ["\"", "interp"], ["1", "adj:sg:nom:n:pos"], [".", "interp"], ["sprzedaż", "subst:sg:dat:f"], ["mieszkanie", "subst:sg:gen:n"], ["dokonywać", "fin:sg:ter:imperf"], ["się", "qub"], ["po", "prep:loc"], ["cena", "subst:sg:loc:f"], ["ustalić", "ppas:sg:loc:f:perf:aff"], ["na", "prep:loc"], ["zasada", "subst:pl:loc:f"], ["określić", "ppas:pl:loc:f:perf:aff"], ["w", "prep:loc:nwok"], ["ustawa", "subst:sg:loc:f"], ["o", "prep:loc"], ["gospodarka", "subst:sg:loc:f"], ["nieruchomość", "subst:pl:inst:f"], ["łącznie", "adv:pos"], ["pomniejszyć", "ppas:sg:gen:f:perf:aff"], ["o", "prep:acc"], [":", "interp"], ["1", "adj:sg:nom:n:pos"], [")", "interp"], ["6", "num:pl:acc:m3:rec"], ["%", "subst:sg:nom:m3"], ["za", "prep:acc"], ["każdy", "adj:sg:acc:m3:pos"], ["rok", "subst:sg:acc:m3"], ["praca", "subst:sg:gen:f"], ["u", "prep:gen"], ["zbywca", "subst:sg:gen:m1"], ["lub", "conj"], ["on", "ppron3:sg:gen:m1:ter:akc:npraep"], ["poprzednik", "subst:sg:gen:m1"], ["prawny", "adj:sg:gen:m3:pos"], [",", "interp"], ["2", "num:pl:acc:f:congr"], [")", "interp"], ["3", "num:pl:acc:m3:congr"], ["%", "subst:sg:nom:m3"], ["za", "prep:acc"], ["każdy", "adj:sg:acc:m3:pos"], ["rok", "subst:sg:acc:m3"], ["najem", "subst:sg:gen:m3"], ["ten", "adj:sg:gen:n:pos"], ["mieszkanie", "subst:sg:gen:n"], ["-", "interp"], ["przy", "prep:loc"], ["co", "subst:sg:loc:n"], ["łączny", "adj:sg:nom:f:pos"], ["obniżka", "subst:sg:nom:f"], ["nie", "qub"], ["móc", "fin:sg:ter:imperf"], ["przekraczać", "inf:imperf"], ["95", "num:pl:gen:m3:rec"], ["%", "subst:sg:nom:m3"], ["cena", "subst:sg:gen:f"], ["sprzedaż", "subst:sg:gen:f"], ["mieszkanie", "subst:sg:gen:n"], [".", "interp"], ["\"", "interp"], [",", "interp"], ["b", "subst:sg:nom:n"], [")", "interp"], ["ustęp", "brev:pun"], [".", "interp"], ["3", "adj:sg:nom:m3:pos"], ["otrzymywać", "fin:sg:ter:imperf"], ["brzmienie", "subst:sg:acc:n"], [":", "interp"], ["\"", "interp"], ["3", "adj:sg:nom:n:pos"], [".", "interp"], ["na", "prep:acc"], ["wniosek", "subst:sg:acc:m3"], ["osoba", "subst:sg:gen:f"], [",", "interp"], ["o", "prep:loc"], ["który", "adj:sg:loc:f:pos"], ["mowa", "subst:sg:nom:f"], ["w", "prep:loc:nwok"], ["artykuł", "brev:pun"], [".", "interp"], ["2", "adj:sg:loc:m3:pos"], ["punkt", "brev:npun"], ["2", "adj:sg:nom:m3:pos"], ["litera", "brev:pun"], [".", "interp"], ["b", "subst:sg:nom:n"], [")", "interp"], [",", "interp"], ["uwzględniać", "fin:sg:ter:imperf"], ["się", "qub"], ["zamiast", "prep:gen"], ["zaliczyć", "ppas:sg:gen:m3:perf:aff"], ["on", "ppron3:sg:gen:f:ter:akc:npraep"], ["okres", "subst:sg:gen:m3"], ["najem", "subst:sg:gen:m3"], [",", "interp"], ["okres", "subst:sg:nom:m3"], ["praca", "subst:sg:gen:f"], ["lub", "conj"], ["najem", "subst:sg:gen:m3"], ["pracownik", "subst:sg:gen:m1"], ["lub", "conj"], ["były", "adj:sg:gen:m1:pos"], ["pracownik", "subst:sg:gen:m1"], ["u", "prep:gen"], ["zbywca", "subst:sg:gen:m1"], ["lub", "conj"], ["u", "prep:gen"], ["on", "ppron3:sg:gen:m1:ter:akc:npraep"], ["poprzednik", "subst:sg:gen:m1"], ["prawny", "adj:sg:gen:m3:pos"], [",", "interp"], ["jeżeli", "comp"], ["być", "fin:sg:ter:imperf"], ["korzystny", "adj:sg:nom:m3:com"], [".", "interp"], ["\"", "interp"], [",", "interp"], ["c", "subst:sg:nom:n"], [")", "interp"], ["dodawać", "fin:sg:ter:imperf"], ["się", "qub"], ["ustęp", "brev:pun"], [".", "interp"], ["4", "adj:sg:gen:m3:pos"], ["w", "prep:loc:nwok"], ["brzmienie", "subst:sg:loc:n"], [":", "interp"], ["\"", "interp"], ["4", "adj:sg:nom:n:pos"], [".", "interp"], ["jeśli", "comp"], ["osoba", "subst:sg:inst:f"], ["uprawniony", "adj:sg:inst:f:pos"], ["być", "fin:sg:ter:imperf"], ["emeryt", "subst:sg:nom:m1"], [",", "interp"], ["rencista", "subst:sg:nom:m1"], ["lub", "conj"], ["wdowa", "subst:sg:nom:f"], ["(", "interp"], ["wdowiec", "subst:sg:nom:m1"], [")", "interp"], ["po", "prep:loc"], ["on", "ppron3:sg:loc:m1:ter:akc:praep"], ["(", "interp"], ["po", "prep:loc"], ["on", "ppron3:sg:loc:f:ter:akc:praep"], [")", "interp"], ["cena", "subst:sg:nom:f"], ["nabyć", "ger:sg:gen:n:perf:aff"], ["mieszkanie", "subst:sg:gen:n"], ["ustalać", "ppas:sg:nom:f:imperf:aff"], ["być", "fin:sg:ter:imperf"], ["na", "prep:acc"], ["5", "num:pl:acc:m3:rec"], ["%", "subst:sg:nom:m3"], ["on", "ppron3:sg:gen:m1:ter:akc:npraep"], ["wartość", "subst:sg:gen:f"], [".", "interp"], ["\"", "interp"], [";", "interp"], ["4", "adj:sg:nom:n:pos"], [")", "interp"], ["w", "prep:loc:nwok"], ["artykuł", "brev:pun"], [".", "interp"], ["10", "adj:sg:loc:m3:pos"], ["dodawać", "fin:sg:ter:imperf"], ["się", "qub"], ["ustęp", "brev:pun"], [".", "interp"], ["3", "adj:sg:gen:m3:pos"], ["w", "prep:loc:nwok"], ["brzmienie", "subst:sg:loc:n"], [":", "interp"], ["\"", "interp"], ["3", "adj:sg:nom:n:pos"], [".", "interp"], ["przepis", "subst:pl:nom:m3"], ["ustęp", "brev:pun"], [".", "interp"], ["1", "adj:sg:gen:m3:pos"], ["i", "conj"], ["2", "adj:sg:gen:m3:pos"], ["mieć", "fin:pl:ter:imperf"], ["zastosowanie", "subst:sg:acc:n"], ["także", "qub"], ["do", "prep:gen"], ["państwowy", "adj:sg:gen:n:pos"], ["gospodarstwo", "subst:sg:gen:n"], ["leśny", "adj:sg:gen:n:pos"], ["las", "subst:pl:nom:m3"], ["państwowy", "adj:pl:nom:m3:pos"], [".", "interp"], ["\"", "interp"], [".", "interp"], ["artykuł", "brev:pun"], [".", "interp"], ["2", "adj:sg:nom:m3:pos"], [".", "interp"], ["ustawa", "subst:sg:nom:f"], ["wchodzić", "fin:sg:ter:imperf"], ["w", "prep:acc:nwok"], ["życie", "subst:sg:acc:n"], ["po", "prep:loc"], ["upływ", "subst:sg:loc:m3"], ["14", "num:pl:gen:m3:congr"], ["dzień", "subst:pl:gen:m3"], ["od", "prep:gen:nwok"], ["dzień", "subst:sg:gen:m3"], ["ogłoszenie", "subst:sg:gen:n"], [".", "interp"]]